plone.app.discussion-5.2.1-py3.13-nspkg.pth
plone/app/discussion/__init__.py
plone/app/discussion/architecture.txt
plone/app/discussion/behavior.py
plone/app/discussion/behavior.zcml
plone/app/discussion/catalog.py
plone/app/discussion/comment.py
plone/app/discussion/comment.txt
plone/app/discussion/configure.zcml
plone/app/discussion/contentrules.py
plone/app/discussion/contentrules.zcml
plone/app/discussion/conversation.py
plone/app/discussion/conversation.txt
plone/app/discussion/design.txt
plone/app/discussion/events.py
plone/app/discussion/interfaces.py
plone/app/discussion/notifications.zcml
plone/app/discussion/permissions.zcml
plone/app/discussion/setuphandlers.py
plone/app/discussion/subscribers.py
plone/app/discussion/subscribers.zcml
plone/app/discussion/testing.py
plone/app/discussion/tool.py
plone/app/discussion/upgrades.py
plone/app/discussion/upgrades.zcml
plone/app/discussion/vocabularies.py
plone/app/discussion/browser/__init__.py
plone/app/discussion/browser/captcha.py
plone/app/discussion/browser/captcha.txt
plone/app/discussion/browser/captcha.zcml
plone/app/discussion/browser/comment.py
plone/app/discussion/browser/comments.pt
plone/app/discussion/browser/comments.py
plone/app/discussion/browser/configure.zcml
plone/app/discussion/browser/controlpanel.pt
plone/app/discussion/browser/controlpanel.py
plone/app/discussion/browser/conversation.py
plone/app/discussion/browser/moderation.pt
plone/app/discussion/browser/moderation.py
plone/app/discussion/browser/restapi.py
plone/app/discussion/browser/traversal.py
plone/app/discussion/browser/utils.py
plone/app/discussion/browser/validator.py
plone/app/discussion/profiles/default/actions.xml
plone/app/discussion/profiles/default/browserlayer.xml
plone/app/discussion/profiles/default/catalog.xml
plone/app/discussion/profiles/default/controlpanel.xml
plone/app/discussion/profiles/default/metadata.xml
plone/app/discussion/profiles/default/registry.xml
plone/app/discussion/profiles/default/rolemap.xml
plone_app_discussion-5.2.1.dist-info/METADATA
plone_app_discussion-5.2.1.dist-info/WHEEL
plone_app_discussion-5.2.1.dist-info/entry_points.txt
plone_app_discussion-5.2.1.dist-info/namespace_packages.txt
plone_app_discussion-5.2.1.dist-info/top_level.txt
plone_app_discussion-5.2.1.dist-info/RECORD
