Metadata-Version: 2.4
Name: plone.app.discussion
Version: 5.2.1
Summary: Enhanced discussion support for Plone
Home-page: https://pypi.org/project/plone.app.discussion
Author: Timo Stollenwerk - Plone Foundation
Author-email: plone-developers@lists.sourceforge.net
License: GPL
Keywords: plone discussion
Classifier: Development Status :: 5 - Production/Stable
Classifier: Environment :: Web Environment
Classifier: Framework :: Plone
Classifier: Framework :: Plone :: 6.1
Classifier: Framework :: Plone :: Core
Classifier: Framework :: Zope :: 5
Classifier: License :: OSI Approved :: GNU General Public License v2 (GPLv2)
Classifier: Operating System :: OS Independent
Classifier: Programming Language :: Python
Classifier: Programming Language :: Python :: 3.10
Classifier: Programming Language :: Python :: 3.11
Classifier: Programming Language :: Python :: 3.12
Requires-Python: >=3.10
Requires-Dist: Products.GenericSetup
Requires-Dist: Products.ZCatalog
Requires-Dist: Products.statusmessages
Requires-Dist: plone.app.event
Requires-Dist: plone.registry
Requires-Dist: plone.resource
Requires-Dist: plone.autoform
Requires-Dist: plone.behavior
Requires-Dist: plone.supermodel
Requires-Dist: plone.uuid
Requires-Dist: setuptools
Requires-Dist: plone.app.layout
Requires-Dist: plone.app.registry
Requires-Dist: plone.app.uuid
Requires-Dist: plone.base
Requires-Dist: plone.indexer
Requires-Dist: plone.z3cform
Requires-Dist: z3c.form>=2.3.3
Requires-Dist: Zope
Provides-Extra: test
Requires-Dist: plone.app.testing; extra == "test"
Requires-Dist: plone.stringinterp; extra == "test"
Requires-Dist: plone.contentrules; extra == "test"
Requires-Dist: plone.app.contentrules; extra == "test"
Requires-Dist: plone.app.contenttypes[test]; extra == "test"
Requires-Dist: plone.app.robotframework; extra == "test"
Requires-Dist: plone.app.vocabularies; extra == "test"
Requires-Dist: plone.dexterity; extra == "test"
Requires-Dist: plone.testing; extra == "test"
Requires-Dist: plone.protect; extra == "test"
Requires-Dist: Products.MailHost; extra == "test"
Requires-Dist: robotsuite; extra == "test"
Requires-Dist: plone.dexterity; extra == "test"
Requires-Dist: python-dateutil; extra == "test"
Dynamic: author
Dynamic: author-email
Dynamic: classifier
Dynamic: description
Dynamic: description-content-type
Dynamic: home-page
Dynamic: keywords
Dynamic: license
Dynamic: provides-extra
Dynamic: requires-dist
Dynamic: requires-python
Dynamic: summary
